audiocodec/LICENSE
audiocodec/README.md
audiocodec/docker-compose.yml
audiocodec/setup.py
audiocodec/assets/comparsion_stats.png
audiocodec/assets/objective_comparisons.png
audiocodec/conf/1gpu.yml
audiocodec/conf/base.yml
audiocodec/dac/__init__.py
audiocodec/dac/__main__.py
audiocodec/dac/compare/__init__.py
audiocodec/dac/compare/encodec.py
audiocodec/dac/model/__init__.py
audiocodec/dac/model/base.py
audiocodec/dac/model/dac.py
audiocodec/dac/model/discriminator.py
audiocodec/dac/nn/__init__.py
audiocodec/dac/nn/layers.py
audiocodec/dac/nn/loss.py
audiocodec/dac/nn/quantize.py
audiocodec/dac/utils/__init__.py
audiocodec/dac/utils/decode.py
audiocodec/dac/utils/encode.py
audiocodec/scripts/compute_entropy.py
audiocodec/scripts/evaluate.py
audiocodec/scripts/get_samples.py
audiocodec/scripts/mushra.py
audiocodec/scripts/organize_daps.py
audiocodec/scripts/save_test_set.py
audiocodec/scripts/train.py
audiocodec/scripts/train_no_adv.py
audiocodec/tests/__init__.py
audiocodec/tests/test_cli.py
audiocodec/tests/test_train.py
audiotools/LICENSE
audiotools/README.md
audiotools/setup.py
audiotools/audiotools/__init__.py
audiotools/audiotools/post.py
audiotools/audiotools/preference.py
audiotools/audiotools/core/__init__.py
audiotools/audiotools/core/audio_signal.py
audiotools/audiotools/core/display.py
audiotools/audiotools/core/dsp.py
audiotools/audiotools/core/effects.py
audiotools/audiotools/core/ffmpeg.py
audiotools/audiotools/core/loudness.py
audiotools/audiotools/core/playback.py
audiotools/audiotools/core/util.py
audiotools/audiotools/core/whisper.py
audiotools/audiotools/core/templates/__init__.py
audiotools/audiotools/core/templates/headers.html
audiotools/audiotools/core/templates/pandoc.css
audiotools/audiotools/core/templates/widget.html
audiotools/audiotools/data/__init__.py
audiotools/audiotools/data/datasets.py
audiotools/audiotools/data/preprocess.py
audiotools/audiotools/data/transforms.py
audiotools/audiotools/metrics/__init__.py
seed_vc-0.4.3.dist-info/METADATA
seed_vc-0.4.3.dist-info/WHEEL
seed_vc-0.4.3.dist-info/entry_points.txt
seed_vc-0.4.3.dist-info/top_level.txt
seed_vc-0.4.3.dist-info/RECORD
