Metadata-Version: 2.4
Name: seed-vc
Version: 0.4.3
Summary: Seed-VC: Zero-shot Voice & Style Conversion
Author-email: Songting Liu <lius0114@e.ntu.edu.sg>, Junhua Chang <junhuac@gmail.com>
License:                     GNU GENERAL PUBLIC LICENSE
Project-URL: Homepage, https://github.com/Plachtaa/seed-vc
Project-URL: Repository, https://github.com/Plachtaa/seed-vc
Project-URL: Issues, https://github.com/Plachtaa/seed-vc/issues
Keywords: voice conversion,speech,audio,deep learning,seed-vc
Classifier: Programming Language :: Python :: 3
Classifier: Programming Language :: Python :: 3 :: Only
Classifier: Programming Language :: Python :: 3.10
Classifier: License :: OSI Approved :: GNU General Public License v3 (GPLv3)
Classifier: Operating System :: OS Independent
Classifier: Topic :: Scientific/Engineering :: Artificial Intelligence
Classifier: Topic :: Multimedia :: Sound/Audio
Requires-Python: >=3.10
Requires-Dist: numpy<2.0,>=1.24
Requires-Dist: scipy>=1.10
Requires-Dist: librosa>=0.10.2
Requires-Dist: soundfile>=0.12.1
Requires-Dist: pydub>=0.25.1
Requires-Dist: huggingface-hub>=0.28.1
Requires-Dist: einops>=0.7
Requires-Dist: munch>=4.0.0
Requires-Dist: transformers>=4.46
Requires-Dist: accelerate>=0.33
Requires-Dist: hydra-core==1.3.2
Requires-Dist: PyYAML>=6.0
Requires-Dist: python-dotenv>=1.0.1
Requires-Dist: resemblyzer>=0.1.3
Requires-Dist: jiwer==3.0.3
Requires-Dist: torch>=2.1
Requires-Dist: torchaudio>=2.1
Requires-Dist: torchvision>=0.16
Requires-Dist: argbind
Requires-Dist: soundfile
Requires-Dist: pyloudnorm
Requires-Dist: importlib-resources
Requires-Dist: julius
Requires-Dist: torchaudio
Requires-Dist: ffmpy
Requires-Dist: ipython
Requires-Dist: rich
Requires-Dist: matplotlib
Requires-Dist: pystoi
Requires-Dist: torch_stoi
Requires-Dist: flatten-dict
Requires-Dist: markdown2
Requires-Dist: randomname
Requires-Dist: protobuf
Requires-Dist: tensorboard
Requires-Dist: tqdm
Provides-Extra: ui
Requires-Dist: gradio>=4; extra == "ui"
Requires-Dist: FreeSimpleGUI>=5.1.1; extra == "ui"
Provides-Extra: realtime
Requires-Dist: sounddevice>=0.5.0; extra == "realtime"
Provides-Extra: asr
Requires-Dist: modelscope==1.18.1; extra == "asr"
Requires-Dist: funasr==1.1.5; extra == "asr"
